gaze_ocr/__init__.py
gaze_ocr/_gaze_ocr.py
gaze_ocr/dragonfly.py
gaze_ocr/eye_tracking.py
gaze_ocr/talon.py
gaze_ocr-0.5.0.dist-info/METADATA
gaze_ocr-0.5.0.dist-info/WHEEL
gaze_ocr-0.5.0.dist-info/licenses/LICENSE
gaze_ocr-0.5.0.dist-info/RECORD
