Metadata-Version: 2.4
Name: gaze-ocr
Version: 0.5.0
Summary: Library for applying OCR to where the user is looking.
Project-URL: Homepage, https://github.com/wolfmanstout/gaze-ocr
Author: James Stout
License-File: LICENSE
Classifier: License :: OSI Approved :: Apache Software License
Classifier: Operating System :: OS Independent
Classifier: Programming Language :: Python :: 3
Requires-Python: >=3.11
Requires-Dist: screen-ocr
Provides-Extra: dragonfly
Requires-Dist: dragonfly2; extra == 'dragonfly'
Requires-Dist: pythonnet; extra == 'dragonfly'
